syntheseus_paroutes/__init__.py
syntheseus_paroutes/files.py
syntheseus_paroutes/inventory.py
syntheseus_paroutes/model.py
syntheseus_paroutes/targets.py
syntheseus_paroutes-0.1.0.dist-info/LICENSE
syntheseus_paroutes-0.1.0.dist-info/METADATA
syntheseus_paroutes-0.1.0.dist-info/WHEEL
syntheseus_paroutes-0.1.0.dist-info/top_level.txt
syntheseus_paroutes-0.1.0.dist-info/RECORD
