Metadata-Version: 2.1
Name: syntheseus-paroutes
Version: 0.1.0
Summary: Syntheseus wrapper for PaRoutes benchmark. 
Author: Austin Tripp, Krzysztof Maziarz
License: MIT License
Requires-Python: >=3.7
License-File: LICENSE
Requires-Dist: syntheseus
Requires-Dist: pandas
Requires-Dist: rdkit
Requires-Dist: keras
